dominance_analysis/__init__.py
dominance_analysis/dominance.py
dominance_analysis/dominance_old.py
dominance_analysis/test.py
dominance_analysis-1.1.9.dist-info/LICENSE
dominance_analysis-1.1.9.dist-info/METADATA
dominance_analysis-1.1.9.dist-info/WHEEL
dominance_analysis-1.1.9.dist-info/top_level.txt
dominance_analysis-1.1.9.dist-info/RECORD
