Metadata-Version: 2.1
Name: dominance-analysis
Version: 1.1.9
Summary: Dominance Analysis
Home-page: https://github.com/bhagatsajan0073/dominance_analysis
Author: Sajan Kumar Bhagat, Kunjithapatham Sivakumar, Shashank Shekhar,Bala Koteshwar Kolluri
Author-email: bhagat.sajan0073@gmail.com, s.vibish@gmail.com, quintshekhar@gmail.com, balakoteshwar@gmail.com
Maintainer: Sajan Kumar Bhagat, Kunjithapatham Sivakumar, Shashank Shekhar, Bala Koteshwar Kolluri
Maintainer-email: bhagat.sajan0073@gmail.com, s.vibish@gmail.com, quintshekhar@gmail.com, balakoteshwar@gmail.com
License: MIT
Keywords: Dominance Analysis,Feature Importance,Feature Selection
Classifier: Programming Language :: Python :: 3.7
Classifier: Programming Language :: Python :: 3.8
Classifier: Programming Language :: Python :: 3.9
Classifier: Programming Language :: Python :: 3.10
Classifier: License :: OSI Approved :: MIT License
Classifier: Operating System :: OS Independent
License-File: LICENSE
Requires-Dist: pandas
Requires-Dist: numpy
Requires-Dist: seaborn
Requires-Dist: matplotlib
Requires-Dist: scikit-learn
Requires-Dist: tqdm
Requires-Dist: plotly
Requires-Dist: cufflinks
Requires-Dist: statsmodels
Requires-Dist: ipywidgets
Requires-Dist: bokeh (==2.4.3)
Requires-Dist: scipy
Requires-Dist: nbformat
